{
  "firstRun": false,
  "initialized": [
    {
      "path": "/",
      "initialized": true
    }
  ],
  "trackedProjects": [
    "/"
  ],
  "checkpointList": [
    {
      "path": "/",
      "date": "2022-06-14",
      "size": 869050
    }
  ],
  "activityHistory": [
    {
      "path": "/",
      "size": [
        {
          "date": "2021-09-11",
          "value": 881
        },
        {
          "date": "2021-09-12",
          "value": 117
        },
        {
          "date": "2021-09-13",
          "value": 1256
        },
        {
          "date": "2021-09-14",
          "value": 2350
        },
        {
          "date": "2021-09-15",
          "value": 2658
        },
        {
          "date": "2021-09-16",
          "value": 2379
        },
        {
          "date": "2021-09-17",
          "value": 2958
        },
        {
          "date": "2021-09-20",
          "value": 3532
        },
        {
          "date": "2021-09-21",
          "value": 504
        },
        {
          "date": "2021-09-22",
          "value": 1326
        },
        {
          "date": "2021-09-23",
          "value": 1170
        },
        {
          "date": "2021-09-24",
          "value": 2420
        },
        {
          "date": "2021-09-29",
          "value": 2117
        },
        {
          "date": "2021-09-30",
          "value": 3672
        },
        {
          "date": "2021-10-01",
          "value": 4392
        },
        {
          "date": "2021-10-04",
          "value": 3282
        },
        {
          "date": "2021-10-05",
          "value": 661
        },
        {
          "date": "2021-10-06",
          "value": 0
        },
        {
          "date": "2021-10-08",
          "value": 715
        },
        {
          "date": "2021-10-09",
          "value": 2175
        },
        {
          "date": "2021-10-10",
          "value": 4296
        },
        {
          "date": "2021-10-11",
          "value": 2247
        },
        {
          "date": "2021-10-12",
          "value": 0
        },
        {
          "date": "2021-10-13",
          "value": 321
        },
        {
          "date": "2021-10-14",
          "value": 1265
        },
        {
          "date": "2021-10-16",
          "value": 0
        },
        {
          "date": "2021-10-18",
          "value": 2643
        },
        {
          "date": "2021-10-15",
          "value": 2347
        },
        {
          "date": "2021-10-19",
          "value": 1661
        },
        {
          "date": "2021-10-21",
          "value": 12918
        },
        {
          "date": "2021-10-22",
          "value": 12
        },
        {
          "date": "2021-10-23",
          "value": 0
        },
        {
          "date": "2021-10-24",
          "value": 0
        },
        {
          "date": "2021-10-25",
          "value": 140
        },
        {
          "date": "2021-11-01",
          "value": 16800
        },
        {
          "date": "2021-11-02",
          "value": 106230
        },
        {
          "date": "2021-11-03",
          "value": 3541
        },
        {
          "date": "2021-11-04",
          "value": 112719
        },
        {
          "date": "2021-11-05",
          "value": 1875
        },
        {
          "date": "2021-11-06",
          "value": 0
        },
        {
          "date": "2021-11-07",
          "value": 2167
        },
        {
          "date": "2021-11-08",
          "value": 6153
        },
        {
          "date": "2021-11-11",
          "value": 728
        },
        {
          "date": "2021-11-12",
          "value": 6702
        },
        {
          "date": "2021-11-15",
          "value": 722
        },
        {
          "date": "2021-11-16",
          "value": 0
        },
        {
          "date": "2021-11-18",
          "value": 21719
        },
        {
          "date": "2021-11-19",
          "value": 60229
        },
        {
          "date": "2021-11-20",
          "value": 303
        },
        {
          "date": "2021-11-21",
          "value": 0
        },
        {
          "date": "2021-11-22",
          "value": 69834
        },
        {
          "date": "2021-11-23",
          "value": 2470
        },
        {
          "date": "2021-11-24",
          "value": 3475
        },
        {
          "date": "2021-11-25",
          "value": 3045
        },
        {
          "date": "2021-11-26",
          "value": 345395
        },
        {
          "date": "2021-11-29",
          "value": 0
        },
        {
          "date": "2021-11-30",
          "value": 472
        },
        {
          "date": "2021-12-01",
          "value": 0
        },
        {
          "date": "2021-12-02",
          "value": 347273
        },
        {
          "date": "2021-12-03",
          "value": 100354
        },
        {
          "date": "2021-12-04",
          "value": 307323
        },
        {
          "date": "2021-12-06",
          "value": 2982
        },
        {
          "date": "2021-12-07",
          "value": 385
        },
        {
          "date": "2021-12-08",
          "value": 966
        },
        {
          "date": "2021-12-09",
          "value": 2868
        },
        {
          "date": "2021-12-10",
          "value": 4093
        },
        {
          "date": "2021-12-05",
          "value": 307323
        },
        {
          "date": "2021-12-11",
          "value": 0
        },
        {
          "date": "2021-12-13",
          "value": 15651
        },
        {
          "date": "2021-12-14",
          "value": 1406
        },
        {
          "date": "2021-12-15",
          "value": 3717
        },
        {
          "date": "2021-12-16",
          "value": 773
        },
        {
          "date": "2021-12-17",
          "value": 1071
        },
        {
          "date": "2021-12-20",
          "value": 8928
        },
        {
          "date": "2021-12-22",
          "value": 4638
        },
        {
          "date": "2022-01-03",
          "value": 20913
        },
        {
          "date": "2022-01-05",
          "value": 12358
        },
        {
          "date": "2022-01-06",
          "value": 87
        },
        {
          "date": "2022-01-07",
          "value": 120244
        },
        {
          "date": "2022-01-10",
          "value": 28643
        },
        {
          "date": "2022-01-11",
          "value": 72427
        },
        {
          "date": "2022-01-12",
          "value": 69078
        },
        {
          "date": "2022-01-13",
          "value": 1228
        },
        {
          "date": "2022-01-14",
          "value": 24555
        },
        {
          "date": "2022-01-15",
          "value": 0
        },
        {
          "date": "2022-01-16",
          "value": 2516
        },
        {
          "date": "2022-01-17",
          "value": 4129
        },
        {
          "date": "2022-01-18",
          "value": 12
        },
        {
          "date": "2022-01-19",
          "value": 36039
        },
        {
          "date": "2022-01-20",
          "value": 32689
        },
        {
          "date": "2022-01-21",
          "value": 4223
        },
        {
          "date": "2022-01-24",
          "value": 3566
        },
        {
          "date": "2022-01-25",
          "value": 4153
        },
        {
          "date": "2022-01-26",
          "value": 2164
        },
        {
          "date": "2022-01-27",
          "value": 423
        },
        {
          "date": "2022-01-28",
          "value": 66339
        },
        {
          "date": "2022-01-29",
          "value": 0
        },
        {
          "date": "2022-01-30",
          "value": 442
        },
        {
          "date": "2022-01-31",
          "value": 5728
        },
        {
          "date": "2022-02-01",
          "value": 701
        },
        {
          "date": "2022-02-02",
          "value": 6223
        },
        {
          "date": "2022-02-03",
          "value": 11106
        },
        {
          "date": "2022-02-04",
          "value": 149
        },
        {
          "date": "2022-02-07",
          "value": 1498
        },
        {
          "date": "2022-02-11",
          "value": 18
        },
        {
          "date": "2022-02-12",
          "value": 0
        },
        {
          "date": "2022-02-13",
          "value": 0
        },
        {
          "date": "2022-02-14",
          "value": 3531
        },
        {
          "date": "2022-02-15",
          "value": 2380
        },
        {
          "date": "2022-02-16",
          "value": 3949
        },
        {
          "date": "2022-02-17",
          "value": 1255
        },
        {
          "date": "2022-02-18",
          "value": 2763
        },
        {
          "date": "2022-02-21",
          "value": 1572
        },
        {
          "date": "2022-02-22",
          "value": 0
        },
        {
          "date": "2022-02-23",
          "value": 15705
        },
        {
          "date": "2022-02-28",
          "value": 1831
        },
        {
          "date": "2022-03-01",
          "value": 0
        },
        {
          "date": "2022-03-02",
          "value": 1421
        },
        {
          "date": "2022-03-03",
          "value": 826
        },
        {
          "date": "2022-03-04",
          "value": 1582
        },
        {
          "date": "2022-03-15",
          "value": 0
        },
        {
          "date": "2022-03-19",
          "value": 1187
        },
        {
          "date": "2022-03-21",
          "value": 5095
        },
        {
          "date": "2022-03-22",
          "value": 0
        },
        {
          "date": "2022-03-23",
          "value": 4012
        },
        {
          "date": "2022-03-24",
          "value": 805
        },
        {
          "date": "2022-03-25",
          "value": 91
        },
        {
          "date": "2022-03-28",
          "value": 4723
        },
        {
          "date": "2022-03-29",
          "value": 0
        },
        {
          "date": "2022-03-30",
          "value": 1830
        },
        {
          "date": "2022-03-31",
          "value": 1737
        },
        {
          "date": "2022-04-01",
          "value": 14
        },
        {
          "date": "2022-04-02",
          "value": 0
        },
        {
          "date": "2022-04-03",
          "value": 0
        },
        {
          "date": "2022-04-04",
          "value": 1015
        },
        {
          "date": "2022-04-06",
          "value": 1758
        },
        {
          "date": "2022-04-08",
          "value": 602
        },
        {
          "date": "2022-04-09",
          "value": 0
        },
        {
          "date": "2022-04-10",
          "value": 0
        },
        {
          "date": "2022-04-11",
          "value": 236
        },
        {
          "date": "2022-04-12",
          "value": 0
        },
        {
          "date": "2022-04-20",
          "value": 1592
        },
        {
          "date": "2022-04-21",
          "value": 684
        },
        {
          "date": "2022-04-22",
          "value": 1988
        },
        {
          "date": "2022-04-25",
          "value": 966
        },
        {
          "date": "2022-04-26",
          "value": 5
        },
        {
          "date": "2022-04-27",
          "value": 691
        },
        {
          "date": "2022-04-28",
          "value": 963
        },
        {
          "date": "2022-04-29",
          "value": 841
        },
        {
          "date": "2022-04-30",
          "value": 0
        },
        {
          "date": "2022-05-01",
          "value": 0
        },
        {
          "date": "2022-05-02",
          "value": 0
        },
        {
          "date": "2022-05-04",
          "value": 1078
        },
        {
          "date": "2022-05-05",
          "value": 1144
        },
        {
          "date": "2022-05-06",
          "value": 1296
        },
        {
          "date": "2022-05-09",
          "value": 2382
        },
        {
          "date": "2022-05-10",
          "value": 0
        },
        {
          "date": "2022-05-11",
          "value": 0
        },
        {
          "date": "2022-05-12",
          "value": 1056
        },
        {
          "date": "2022-05-13",
          "value": 1622
        },
        {
          "date": "2022-05-15",
          "value": 0
        },
        {
          "date": "2022-05-16",
          "value": 477
        },
        {
          "date": "2022-05-17",
          "value": 0
        },
        {
          "date": "2022-05-18",
          "value": 138
        },
        {
          "date": "2022-05-24",
          "value": 74
        },
        {
          "date": "2022-05-25",
          "value": 0
        },
        {
          "date": "2022-05-26",
          "value": 0
        },
        {
          "date": "2022-05-27",
          "value": 0
        },
        {
          "date": "2022-06-04",
          "value": 158
        },
        {
          "date": "2022-06-06",
          "value": 1053
        },
        {
          "date": "2022-06-07",
          "value": 1008
        },
        {
          "date": "2022-06-08",
          "value": 1125
        },
        {
          "date": "2022-06-09",
          "value": 17150
        },
        {
          "date": "2022-06-10",
          "value": 0
        },
        {
          "date": "2022-06-13",
          "value": 8738
        },
        {
          "date": "2022-06-14",
          "value": 221
        }
      ]
    }
  ],
  "activityColor1": "#c6e48b",
  "activityColor2": "#7bc96f",
  "activityColor3": "#239a3b",
  "activityColor4": "#196127",
  "textColor": "#000000",
  "emptyColor": "#ecedf0",
  "cellRadius": 1,
  "type": "yearly"
}